generated_code/generated.v
module TOP_CASEZ(CLK, RST, cnt);
  input CLK, RST;
  output reg [7:0] cnt;

  always @(posedge CLK) begin
    if (RST) begin
      cnt <= 0;
    end else begin
      casez(cnt)
        8'b00000000: begin
          cnt <= cnt + 1;
        end
        8'b1???????: begin
          cnt <= 0;
        end
        default: begin
          cnt <= cnt + 1;
        end
      endcase
    end
  end
endmodule

generated_code/testbench.v
`timescale 1ns / 1ps

module tb_TOP_CASEZ;
    reg CLK;
    reg RST;
    wire [7:0] cnt;

    // Instantiate the TOP_CASEZ module
    TOP_CASEZ uut (
        .CLK(CLK),
        .RST(RST),
        .cnt(cnt)
    );

    // Clock generation: 10ns period (100 MHz)
    always begin
        #5 CLK = ~CLK;
    end

    // Test cases
    initial begin
        CLK = 0;
        RST = 1;  // Apply reset
        $display("Starting TOP_CASEZ Testbench...");
        $dumpfile("top_casez_tb.vcd");
        $dumpvars(0, tb_TOP_CASEZ);
        
        #10 RST = 0;  // Release reset

        #100 RST = 1; // Apply reset again
        #10  RST = 0; // Release reset

        // Let the counter run
        #200;

        $display("Testbench completed.");
        $finish;
    end

    // Monitor outputs
    initial begin
        $monitor("Time: %0t | CLK: %b | RST: %b | cnt: %h", $time, CLK, RST, cnt);
    end
endmodule

top_casez_tb.vcd
$date
	Tue May  6 20:38:12 2025
$end
$version
	Icarus Verilog
$end
$timescale
	1ps
$end
$scope module tb_TOP_CASEZ $end
$var wire 8 ! cnt [7:0] $end
$var reg 1 " CLK $end
$var reg 1 # RST $end
$scope module uut $end
$var wire 1 " CLK $end
$var wire 1 # RST $end
$var reg 8 $ cnt [7:0] $end
$upscope $end
$upscope $end
$enddefinitions $end
#0
$dumpvars
bx $
1#
0"
bx !
$end
#5000
b0 !
b0 $
1"
#10000
0"
0#
#15000
b1 !
b1 $
1"
#20000
0"
#25000
b10 !
b10 $
1"
#30000
0"
#35000
b11 !
b11 $
1"
#40000
0"
#45000
b100 !
b100 $
1"
#50000
0"
#55000
b101 !
b101 $
1"
#60000
0"
#65000
b110 !
b110 $
1"
#70000
0"
#75000
b111 !
b111 $
1"
#80000
0"
#85000
b1000 !
b1000 $
1"
#90000
0"
#95000
b1001 !
b1001 $
1"
#100000
0"
#105000
b1010 !
b1010 $
1"
#110000
0"
1#
#115000
b0 !
b0 $
1"
#120000
0"
0#
#125000
b1 !
b1 $
1"
#130000
0"
#135000
b10 !
b10 $
1"
#140000
0"
#145000
b11 !
b11 $
1"
#150000
0"
#155000
b100 !
b100 $
1"
#160000
0"
#165000
b101 !
b101 $
1"
#170000
0"
#175000
b110 !
b110 $
1"
#180000
0"
#185000
b111 !
b111 $
1"
#190000
0"
#195000
b1000 !
b1000 $
1"
#200000
0"
#205000
b1001 !
b1001 $
1"
#210000
0"
#215000
b1010 !
b1010 $
1"
#220000
0"
#225000
b1011 !
b1011 $
1"
#230000
0"
#235000
b1100 !
b1100 $
1"
#240000
0"
#245000
b1101 !
b1101 $
1"
#250000
0"
#255000
b1110 !
b1110 $
1"
#260000
0"
#265000
b1111 !
b1111 $
1"
#270000
0"
#275000
b10000 !
b10000 $
1"
#280000
0"
#285000
b10001 !
b10001 $
1"
#290000
0"
#295000
b10010 !
b10010 $
1"
#300000
0"
#305000
b10011 !
b10011 $
1"
#310000
0"
#315000
b10100 !
b10100 $
1"
